forks/__init__.py
forks/utils.py
forks-0.0.1.dist-info/METADATA
forks-0.0.1.dist-info/WHEEL
forks-0.0.1.dist-info/RECORD
